pytinsel/__init__.py
pytinsel/functions.py
pytinsel-0.0.1.dist-info/DESCRIPTION.rst
pytinsel-0.0.1.dist-info/METADATA
pytinsel-0.0.1.dist-info/RECORD
pytinsel-0.0.1.dist-info/WHEEL
pytinsel-0.0.1.dist-info/metadata.json
pytinsel-0.0.1.dist-info/top_level.txt
